paho/__init__.py
paho/mqtt/__init__.py
paho/mqtt/client.py
paho/mqtt/enums.py
paho/mqtt/matcher.py
paho/mqtt/packettypes.py
paho/mqtt/properties.py
paho/mqtt/publish.py
paho/mqtt/py.typed
paho/mqtt/reasoncodes.py
paho/mqtt/subscribe.py
paho/mqtt/subscribeoptions.py
tb_paho_mqtt_client-2.1.2.dist-info/METADATA
tb_paho_mqtt_client-2.1.2.dist-info/WHEEL
tb_paho_mqtt_client-2.1.2.dist-info/licenses/LICENSE.txt
tb_paho_mqtt_client-2.1.2.dist-info/RECORD
