Metadata-Version: 2.4
Name: tb-paho-mqtt-client
Version: 2.1.2
Summary: MQTT version 5.0/3.1.1 client class
Project-URL: Homepage, http://eclipse.org/paho
Author-email: Roger Light <roger@atchoo.org>
License: EPL-2.0 OR BSD-3-Clause
License-File: LICENSE.txt
Keywords: paho
Classifier: Development Status :: 4 - Beta
Classifier: Intended Audience :: Developers
Classifier: License :: OSI Approved
Classifier: Natural Language :: English
Classifier: Operating System :: MacOS :: MacOS X
Classifier: Operating System :: Microsoft :: Windows
Classifier: Operating System :: POSIX
Classifier: Programming Language :: Python
Classifier: Programming Language :: Python :: 3
Classifier: Programming Language :: Python :: 3.7
Classifier: Programming Language :: Python :: 3.8
Classifier: Programming Language :: Python :: 3.9
Classifier: Programming Language :: Python :: 3.10
Classifier: Topic :: Communications
Classifier: Topic :: Internet
Requires-Python: >=3.7
Provides-Extra: proxy
Requires-Dist: pysocks; extra == 'proxy'
